{"name":"Contrôler un afficheur LCD avec une liaison série","tagline":"Programme de test en C# et description de la classe SerialELCD162","body":"### Afficheur LCD 2 x 16 caractères à commandes séries.\r\nCet afficheur LCD \"OEM\" à commandes séries est composé d'un afficheur LCD standard associé à une platine de commande pouvant être commandée par un microcontrôleur au moyen d'ordres séries (**8 bits - sans parité - 1 bit de stop - débit binaire 19200b/s ou 4800 b/s**). L'afficheur (à processeur Hitachi) dispose d'un réglage de contraste au moyen d'un potentiomètre présent sur la platine de commande.\r\n\r\n![](http://www.lextronic.fr/imagelib/15/elcd162a.jpg)\r\n\r\n* **Alimentation**: 5V\r\n* **Commande** : liaison série asynchrone 8 bits - sans parité - 1 bit de stop - débit binaire 19200b/s ou 4800 b/s\r\n* **Dimensions**: 80mm x 36mm\r\n* **Documentation** : [Comfile ELCD162](http://www.lextronic.fr/lextronic_doc/ELCD.pdf)\r\n* **Distributeur**: [Lextronic](http://www.lextronic.fr/P761-afficheur-2-x-16-caracteres-non-retro-eclaire.html)\r\n\r\n### Carte Netduino plus 2\r\n\r\n### Classe SerialELCD162 ","google":"","note":"Don't delete this file! It's used internally to help with page regeneration."}